picsi/__init__.py
picsi/commands/__init__.py
picsi/commands/build.py
picsi/commands/disable.py
picsi/commands/down.py
picsi/commands/enable.py
picsi/commands/install.py
picsi/commands/status.py
picsi/commands/uninstall.py
picsi/commands/up.py
picsi/picsi.py
picsi/scripts/mkusb.sh
picsi/scripts/picsi-ci.toml
picsi/scripts/rmusb.sh
picsi/vendored/__init__.py
picsi/vendored/ci_read_author.py
picsi/vendored/ci_read_distdate.py
picsi/vendored/ci_read_distlink.py
picsi/vendored/ci_read_githash.py
picsi/vendored/ci_resolve_proxy.py
picsi/vendored/get_architecture.py
picsi/vendored/get_brcmfmacko.py
picsi/vendored/get_output.py
picsi/vendored/get_uname.py
picsi/vendored/mkmanifest.py
picsi/vendored/run_commands.py
picsi-0.0.13.dist-info/entry_points.txt
picsi-0.0.13.dist-info/WHEEL
picsi-0.0.13.dist-info/METADATA
picsi-0.0.13.dist-info/RECORD
