Metadata-Version: 2.1
Name: picsi
Version: 0.0.13
Summary: CSI collection on Raspberry Pi
Home-page: https://github.com/nexmonster/picsi.git
License: MIT
Keywords: Nexmon,CSI,Nexmon_CSI,WiFi
Author: Aravind Reddy Voggu
Author-email: zerodividedby0@gmail.com
Maintainer: Aravind Reddy Voggu
Maintainer-email: zerodividedby0@gmail.com
Requires-Python: >=3.7,<4.0
Classifier: License :: OSI Approved :: MIT License
Classifier: Programming Language :: Python :: 3
Classifier: Programming Language :: Python :: 3.10
Classifier: Programming Language :: Python :: 3.7
Classifier: Programming Language :: Python :: 3.8
Classifier: Programming Language :: Python :: 3.9
Requires-Dist: halo (>=0.0.31,<0.0.32)
Requires-Dist: requests (>=2.27.1,<3.0.0)
Requires-Dist: tomli (>=2.0.0,<3.0.0)
Requires-Dist: tomli-w (>=1.0.0,<2.0.0)
Requires-Dist: typer[all] (>=0.4.0,<0.5.0)
Project-URL: Repository, https://github.com/nexmonster/picsi.git
